ducklake/__init__.py
ducklake/example.py
ducklake-0.1.0.dist-info/licenses/LICENSE
ducklake-0.1.0.dist-info/METADATA
ducklake-0.1.0.dist-info/WHEEL
ducklake-0.1.0.dist-info/top_level.txt
ducklake-0.1.0.dist-info/RECORD
